{
  "symbol": "ES",
  "ticker": "SPY",
  "timestamp": "2026-05-15T16:05:06.783788",
  "spot": 739.8400268554688,
  "key_levels": {
    "flip_point": 365.0,
    "call_wall": 745.0,
    "put_wall": 738.0,
    "net_gex": -2942651874.87,
    "spot": 739.8400268554688
  },
  "gex_by_expiry": {
    "2026-05-15": {
      "net_gex": -1629879927.83,
      "call_gex": 5525053680.87,
      "put_gex": -7154933608.7
    },
    "2026-05-18": {
      "net_gex": -663953556.02,
      "call_gex": 789754025.3,
      "put_gex": -1453707581.32
    },
    "2026-05-19": {
      "net_gex": -274133596.64,
      "call_gex": 349498412.89,
      "put_gex": -623632009.53
    },
    "2026-05-20": {
      "net_gex": -374684794.37,
      "call_gex": 256617069.11,
      "put_gex": -631301863.48
    }
  },
  "gex_by_strike": [
    {
      "strike": 360.0,
      "call_gex": 5210.102440654558,
      "put_gex": -9392.49789627365,
      "net_gex": -4182.395455619091,
      "expiry": "2026-05-15"
    },
    {
      "strike": 365.0,
      "call_gex": 5071.22873940975,
      "put_gex": -4720.6089057669,
      "net_gex": 350.6198336428506,
      "expiry": "2026-05-15"
    },
    {
      "strike": 370.0,
      "call_gex": 163.86180772332312,
      "put_gex": -5364.974062225543,
      "net_gex": -5201.11225450222,
      "expiry": "2026-05-15"
    },
    {
      "strike": 375.0,
      "call_gex": 0.0,
      "put_gex": -5663.0480946964535,
      "net_gex": -5663.0480946964535,
      "expiry": "2026-05-15"
    },
    {
      "strike": 380.0,
      "call_gex": 0.0,
      "put_gex": -4661.952092675952,
      "net_gex": -4661.952092675952,
      "expiry": "2026-05-15"
    },
    {
      "strike": 385.0,
      "call_gex": 0.0,
      "put_gex": -21039.294372096054,
      "net_gex": -21039.294372096054,
      "expiry": "2026-05-15"
    },
    {
      "strike": 390.0,
      "call_gex": 0.0,
      "put_gex": -5877.207980895744,
      "net_gex": -5877.207980895744,
      "expiry": "2026-05-15"
    },
    {
      "strike": 395.0,
      "call_gex": 861.0138162766758,
      "put_gex": -11054.952877962536,
      "net_gex": -10193.93906168586,
      "expiry": "2026-05-15"
    },
    {
      "strike": 400.0,
      "call_gex": 2429.2834181521075,
      "put_gex": -59889.73358720957,
      "net_gex": -57460.45016905746,
      "expiry": "2026-05-15"
    },
    {
      "strike": 405.0,
      "call_gex": 840.6357399610056,
      "put_gex": -20527.598454718955,
      "net_gex": -19686.96271475795,
      "expiry": "2026-05-15"
    },
    {
      "strike": 410.0,
      "call_gex": 848.6872458309089,
      "put_gex": -7573.461728123934,
      "net_gex": -6724.774482293025,
      "expiry": "2026-05-15"
    },
    {
      "strike": 415.0,
      "call_gex": 0.0,
      "put_gex": -4096.3702733314385,
      "net_gex": -4096.3702733314385,
      "expiry": "2026-05-15"
    },
    {
      "strike": 420.0,
      "call_gex": 1668.5464354997985,
      "put_gex": -7240.152613756684,
      "net_gex": -5571.606178256886,
      "expiry": "2026-05-15"
    },
    {
      "strike": 425.0,
      "call_gex": 957.1135764986508,
      "put_gex": -33788.67186649358,
      "net_gex": -32831.55828999493,
      "expiry": "2026-05-15"
    },
    {
      "strike": 430.0,
      "call_gex": 85446.24300992214,
      "put_gex": -7064.0998411944975,
      "net_gex": 78382.14316872763,
      "expiry": "2026-05-15"
    },
    {
      "strike": 435.0,
      "call_gex": 2404.527984432807,
      "put_gex": -8339.622284631027,
      "net_gex": -5935.09430019822,
      "expiry": "2026-05-15"
    },
    {
      "strike": 440.0,
      "call_gex": 2187.7000901546,
      "put_gex": -10771.050744785976,
      "net_gex": -8583.350654631377,
      "expiry": "2026-05-15"
    },
    {
      "strike": 445.0,
      "call_gex": 0.0,
      "put_gex": -267293.3630400393,
      "net_gex": -267293.3630400393,
      "expiry": "2026-05-15"
    },
    {
      "strike": 450.0,
      "call_gex": 1502.379178609342,
      "put_gex": -345506.2473264599,
      "net_gex": -344003.86814785056,
      "expiry": "2026-05-15"
    },
    {
      "strike": 455.0,
      "call_gex": 150.11808650062332,
      "put_gex": -23667.456793750174,
      "net_gex": -23517.33870724955,
      "expiry": "2026-05-15"
    },
    {
      "strike": 460.0,
      "call_gex": 315.4912410563874,
      "put_gex": -11325.034382522876,
      "net_gex": -11009.543141466489,
      "expiry": "2026-05-15"
    },
    {
      "strike": 465.0,
      "call_gex": 458.1870800430273,
      "put_gex": -6678.21055219498,
      "net_gex": -6220.023472151953,
      "expiry": "2026-05-15"
    },
    {
      "strike": 470.0,
      "call_gex": 2461.739677176783,
      "put_gex": -17103.781621724796,
      "net_gex": -14642.041944548013,
      "expiry": "2026-05-15"
    },
    {
      "strike": 475.0,
      "call_gex": 4664.749043307989,
      "put_gex": -24176.373364457755,
      "net_gex": -19511.624321149764,
      "expiry": "2026-05-15"
    },
    {
      "strike": 480.0,
      "call_gex": 1984.6286412168754,
      "put_gex": -351892.2821405935,
      "net_gex": -349907.6534993766,
      "expiry": "2026-05-15"
    },
    {
      "strike": 485.0,
      "call_gex": 918.1422334700695,
      "put_gex": -8333.105482440604,
      "net_gex": -7414.963248970535,
      "expiry": "2026-05-15"
    },
    {
      "strike": 490.0,
      "call_gex": 6283.264322320923,
      "put_gex": -11621.229252757032,
      "net_gex": -5337.964930436108,
      "expiry": "2026-05-15"
    },
    {
      "strike": 495.0,
      "call_gex": 3472.129272561329,
      "put_gex": -975744.6992575588,
      "net_gex": -972272.5699849975,
      "expiry": "2026-05-15"
    },
    {
      "strike": 500.0,
      "call_gex": 67905.43626466482,
      "put_gex": -1001314.1148275434,
      "net_gex": -933408.6785628785,
      "expiry": "2026-05-152026-05-182026-05-192026-05-20"
    },
    {
      "strike": 505.0,
      "call_gex": 14420.608362719213,
      "put_gex": -29069.989170006742,
      "net_gex": -14649.380807287529,
      "expiry": "2026-05-15"
    },
    {
      "strike": 510.0,
      "call_gex": 6154.0984667263765,
      "put_gex": -13420.6182901164,
      "net_gex": -7266.519823390022,
      "expiry": "2026-05-152026-05-182026-05-20"
    },
    {
      "strike": 515.0,
      "call_gex": 17374.877724370395,
      "put_gex": -12997.636887429107,
      "net_gex": 4377.240836941288,
      "expiry": "2026-05-15"
    },
    {
      "strike": 520.0,
      "call_gex": 10475.62623316392,
      "put_gex": -60639.194474221855,
      "net_gex": -50163.56824105794,
      "expiry": "2026-05-152026-05-182026-05-19"
    },
    {
      "strike": 525.0,
      "call_gex": 18599.92799358737,
      "put_gex": -47145.94710105707,
      "net_gex": -28546.0191074697,
      "expiry": "2026-05-15"
    },
    {
      "strike": 530.0,
      "call_gex": 40423.04079455045,
      "put_gex": -1289308.5647446513,
      "net_gex": -1248885.5239501009,
      "expiry": "2026-05-152026-05-19"
    },
    {
      "strike": 535.0,
      "call_gex": 90993.83075576839,
      "put_gex": -43189.75636874387,
      "net_gex": 47804.07438702452,
      "expiry": "2026-05-152026-05-182026-05-192026-05-20"
    },
    {
      "strike": 540.0,
      "call_gex": 12010.320951750848,
      "put_gex": -120850.439178717,
      "net_gex": -108840.11822696615,
      "expiry": "2026-05-152026-05-182026-05-19"
    },
    {
      "strike": 545.0,
      "call_gex": 13136.865436285756,
      "put_gex": -729138.5843391203,
      "net_gex": -716001.7189028346,
      "expiry": "2026-05-152026-05-182026-05-20"
    },
    {
      "strike": 550.0,
      "call_gex": 21974.29439950438,
      "put_gex": -1209204.2256150239,
      "net_gex": -1187229.9312155196,
      "expiry": "2026-05-152026-05-182026-05-192026-05-20"
    },
    {
      "strike": 555.0,
      "call_gex": 4995.924539504657,
      "put_gex": -82267.76291843125,
      "net_gex": -77271.8383789266,
      "expiry": "2026-05-152026-05-19"
    },
    {
      "strike": 560.0,
      "call_gex": 20713.74741055099,
      "put_gex": -351096.8896732769,
      "net_gex": -330383.1422627259,
      "expiry": "2026-05-152026-05-192026-05-20"
    },
    {
      "strike": 565.0,
      "call_gex": 510948.8505253716,
      "put_gex": -95030.39019644092,
      "net_gex": 415918.4603289307,
      "expiry": "2026-05-152026-05-192026-05-20"
    },
    {
      "strike": 570.0,
      "call_gex": 1808606.525331525,
      "put_gex": -353683.20270822255,
      "net_gex": 1454923.3226233022,
      "expiry": "2026-05-152026-05-182026-05-20"
    },
    {
      "strike": 575.0,
      "call_gex": 596670.9089935268,
      "put_gex": -661701.2298875329,
      "net_gex": -65030.320894006014,
      "expiry": "2026-05-152026-05-182026-05-19"
    },
    {
      "strike": 580.0,
      "call_gex": 362136.0633367217,
      "put_gex": -1216209.7465033636,
      "net_gex": -854073.6831666419,
      "expiry": "2026-05-152026-05-182026-05-192026-05-20"
    },
    {
      "strike": 585.0,
      "call_gex": 434567.81506640994,
      "put_gex": -152383.82969058,
      "net_gex": 282183.9853758299,
      "expiry": "2026-05-152026-05-182026-05-20"
    },
    {
      "strike": 590.0,
      "call_gex": 624472.6928746328,
      "put_gex": -377225.8076390052,
      "net_gex": 247246.8852356276,
      "expiry": "2026-05-152026-05-182026-05-192026-05-20"
    },
    {
      "strike": 595.0,
      "call_gex": 973062.236031915,
      "put_gex": -302130.23456378607,
      "net_gex": 670932.0014681289,
      "expiry": "2026-05-152026-05-182026-05-192026-05-20"
    },
    {
      "strike": 600.0,
      "call_gex": 627850.2205045469,
      "put_gex": -1336021.8307272033,
      "net_gex": -708171.6102226563,
      "expiry": "2026-05-152026-05-182026-05-19"
    },
    {
      "strike": 601.0,
      "call_gex": 0.0,
      "put_gex": -113563.69602104716,
      "net_gex": -113563.69602104716,
      "expiry": "2026-05-15"
    },
    {
      "strike": 602.0,
      "call_gex": 547.316762154353,
      "put_gex": -128261.14518084282,
      "net_gex": -127713.82841868847,
      "expiry": "2026-05-15"
    },
    {
      "strike": 603.0,
      "call_gex": 0.0,
      "put_gex": -17007.778721491795,
      "net_gex": -17007.778721491795,
      "expiry": "2026-05-15"
    },
    {
      "strike": 604.0,
      "call_gex": 0.0,
      "put_gex": -11355.188986987368,
      "net_gex": -11355.188986987368,
      "expiry": "2026-05-15"
    },
    {
      "strike": 605.0,
      "call_gex": 851514.5322498486,
      "put_gex": -448701.7562821287,
      "net_gex": 402812.7759677199,
      "expiry": "2026-05-152026-05-182026-05-192026-05-20"
    },
    {
      "strike": 606.0,
      "call_gex": 3435.400121563713,
      "put_gex": -31783.417899877524,
      "net_gex": -28348.01777831381,
      "expiry": "2026-05-15"
    },
    {
      "strike": 607.0,
      "call_gex": 1131.7523916312778,
      "put_gex": -32241.01640833625,
      "net_gex": -31109.264016704972,
      "expiry": "2026-05-15"
    },
    {
      "strike": 608.0,
      "call_gex": 566984.4166355429,
      "put_gex": -10694.982083278042,
      "net_gex": 556289.4345522649,
      "expiry": "2026-05-15"
    },
    {
      "strike": 609.0,
      "call_gex": 0.0,
      "put_gex": -35210.88902628966,
      "net_gex": -35210.88902628966,
      "expiry": "2026-05-15"
    },
    {
      "strike": 610.0,
      "call_gex": 865155.802071522,
      "put_gex": -442433.6355478405,
      "net_gex": 422722.1665236815,
      "expiry": "2026-05-152026-05-182026-05-19"
    },
    {
      "strike": 611.0,
      "call_gex": 0.0,
      "put_gex": -70819.63783113273,
      "net_gex": -70819.63783113273,
      "expiry": "2026-05-15"
    },
    {
      "strike": 612.0,
      "call_gex": 607652.6926962732,
      "put_gex": -81713.3475430318,
      "net_gex": 525939.3451532414,
      "expiry": "2026-05-15"
    },
    {
      "strike": 613.0,
      "call_gex": 0.0,
      "put_gex": -123309.92179173496,
      "net_gex": -123309.92179173496,
      "expiry": "2026-05-15"
    },
    {
      "strike": 614.0,
      "call_gex": 0.0,
      "put_gex": -154316.39654449644,
      "net_gex": -154316.39654449644,
      "expiry": "2026-05-15"
    },
    {
      "strike": 615.0,
      "call_gex": 528926.8550250768,
      "put_gex": -516435.4863601595,
      "net_gex": 12491.368664917234,
      "expiry": "2026-05-152026-05-182026-05-20"
    },
    {
      "strike": 616.0,
      "call_gex": 0.0,
      "put_gex": -14404.949592025805,
      "net_gex": -14404.949592025805,
      "expiry": "2026-05-15"
    },
    {
      "strike": 617.0,
      "call_gex": 0.0,
      "put_gex": -34874.52440016347,
      "net_gex": -34874.52440016347,
      "expiry": "2026-05-15"
    },
    {
      "strike": 618.0,
      "call_gex": 0.0,
      "put_gex": -11304.60977416124,
      "net_gex": -11304.60977416124,
      "expiry": "2026-05-15"
    },
    {
      "strike": 619.0,
      "call_gex": 1300.7742378522876,
      "put_gex": -26389.896322739503,
      "net_gex": -25089.122084887214,
      "expiry": "2026-05-15"
    },
    {
      "strike": 620.0,
      "call_gex": 5010942.226059087,
      "put_gex": -1146753.6611443642,
      "net_gex": 3864188.5649147225,
      "expiry": "2026-05-152026-05-192026-05-20"
    },
    {
      "strike": 621.0,
      "call_gex": 20787.902052697857,
      "put_gex": -15611.003408102375,
      "net_gex": 5176.8986445954815,
      "expiry": "2026-05-15"
    },
    {
      "strike": 622.0,
      "call_gex": 0.0,
      "put_gex": -19774.220173308033,
      "net_gex": -19774.220173308033,
      "expiry": "2026-05-15"
    },
    {
      "strike": 623.0,
      "call_gex": 0.0,
      "put_gex": -15153.033899684504,
      "net_gex": -15153.033899684504,
      "expiry": "2026-05-15"
    },
    {
      "strike": 624.0,
      "call_gex": 0.0,
      "put_gex": -20463.16917149237,
      "net_gex": -20463.16917149237,
      "expiry": "2026-05-15"
    },
    {
      "strike": 625.0,
      "call_gex": 378063.10091764963,
      "put_gex": -1348887.5697881915,
      "net_gex": -970824.4688705419,
      "expiry": "2026-05-152026-05-182026-05-19"
    },
    {
      "strike": 626.0,
      "call_gex": 1466.6772180378018,
      "put_gex": -63456.385889936995,
      "net_gex": -61989.70867189919,
      "expiry": "2026-05-15"
    },
    {
      "strike": 627.0,
      "call_gex": 0.0,
      "put_gex": -201105.2986785304,
      "net_gex": -201105.2986785304,
      "expiry": "2026-05-15"
    },
    {
      "strike": 628.0,
      "call_gex": 0.0,
      "put_gex": -278893.1835693703,
      "net_gex": -278893.1835693703,
      "expiry": "2026-05-15"
    },
    {
      "strike": 629.0,
      "call_gex": 0.0,
      "put_gex": -65963.05725166292,
      "net_gex": -65963.05725166292,
      "expiry": "2026-05-15"
    },
    {
      "strike": 630.0,
      "call_gex": 1212621.0556934439,
      "put_gex": -1337848.93201332,
      "net_gex": -125227.87631987625,
      "expiry": "2026-05-152026-05-182026-05-192026-05-20"
    },
    {
      "strike": 631.0,
      "call_gex": 0.0,
      "put_gex": -25095.4670084334,
      "net_gex": -25095.4670084334,
      "expiry": "2026-05-15"
    },
    {
      "strike": 632.0,
      "call_gex": 0.0,
      "put_gex": -46138.4809953054,
      "net_gex": -46138.4809953054,
      "expiry": "2026-05-15"
    },
    {
      "strike": 633.0,
      "call_gex": 7934.40247468422,
      "put_gex": -90877.52707101332,
      "net_gex": -82943.1245963291,
      "expiry": "2026-05-15"
    },
    {
      "strike": 634.0,
      "call_gex": 100084.89691231979,
      "put_gex": -128966.74367520862,
      "net_gex": -28881.846762888832,
      "expiry": "2026-05-15"
    },
    {
      "strike": 635.0,
      "call_gex": 6547800.259836255,
      "put_gex": -1215451.9895741292,
      "net_gex": 5332348.270262125,
      "expiry": "2026-05-152026-05-182026-05-192026-05-20"
    },
    {
      "strike": 636.0,
      "call_gex": 1637.3236323661945,
      "put_gex": -51758.99831359899,
      "net_gex": -50121.6746812328,
      "expiry": "2026-05-15"
    },
    {
      "strike": 637.0,
      "call_gex": 0.0,
      "put_gex": -22785.24622872797,
      "net_gex": -22785.24622872797,
      "expiry": "2026-05-15"
    },
    {
      "strike": 638.0,
      "call_gex": 1729.3454557643902,
      "put_gex": -47104.767201081726,
      "net_gex": -45375.42174531733,
      "expiry": "2026-05-15"
    },
    {
      "strike": 639.0,
      "call_gex": 2546.6977117019055,
      "put_gex": -41477.46625913107,
      "net_gex": -38930.768547429165,
      "expiry": "2026-05-15"
    },
    {
      "strike": 640.0,
      "call_gex": 6457577.68107771,
      "put_gex": -2173729.4188571945,
      "net_gex": 4283848.262220516,
      "expiry": "2026-05-152026-05-182026-05-192026-05-20"
    },
    {
      "strike": 641.0,
      "call_gex": 16867.84138546616,
      "put_gex": -26235.53576840833,
      "net_gex": -9367.694382942169,
      "expiry": "2026-05-15"
    },
    {
      "strike": 642.0,
      "call_gex": 60378.16854330148,
      "put_gex": -43931.295232480494,
      "net_gex": 16446.873310820985,
      "expiry": "2026-05-15"
    },
    {
      "strike": 643.0,
      "call_gex": 2739.1892934208186,
      "put_gex": -77272.11041750203,
      "net_gex": -74532.92112408121,
      "expiry": "2026-05-15"
    },
    {
      "strike": 644.0,
      "call_gex": 224522.0792882163,
      "put_gex": -37134.97117028105,
      "net_gex": 187387.10811793525,
      "expiry": "2026-05-15"
    },
    {
      "strike": 645.0,
      "call_gex": 2481528.6866504718,
      "put_gex": -827133.4829096596,
      "net_gex": 1654395.2037408121,
      "expiry": "2026-05-152026-05-182026-05-192026-05-20"
    },
    {
      "strike": 646.0,
      "call_gex": 5726.956976742807,
      "put_gex": -29326.509464819384,
      "net_gex": -23599.552488076577,
      "expiry": "2026-05-15"
    },
    {
      "strike": 647.0,
      "call_gex": 984.235425264267,
      "put_gex": -46306.86899720199,
      "net_gex": -45322.633571937724,
      "expiry": "2026-05-15"
    },
    {
      "strike": 648.0,
      "call_gex": 7898.777304228805,
      "put_gex": -30584.6150912845,
      "net_gex": -22685.837787055694,
      "expiry": "2026-05-15"
    },
    {
      "strike": 649.0,
      "call_gex": 14295.447823657896,
      "put_gex": -64828.48842995383,
      "net_gex": -50533.04060629594,
      "expiry": "2026-05-15"
    },
    {
      "strike": 650.0,
      "call_gex": 8093971.156620986,
      "put_gex": -5113860.696438914,
      "net_gex": 2980110.4601820717,
      "expiry": "2026-05-152026-05-182026-05-192026-05-20"
    },
    {
      "strike": 651.0,
      "call_gex": 1157617.9695751069,
      "put_gex": -157984.37869967456,
      "net_gex": 999633.5908754324,
      "expiry": "2026-05-15"
    },
    {
      "strike": 652.0,
      "call_gex": 1526519.7029068004,
      "put_gex": -126491.46346708051,
      "net_gex": 1400028.2394397198,
      "expiry": "2026-05-15"
    },
    {
      "strike": 653.0,
      "call_gex": 1161430.7313645193,
      "put_gex": -155621.60734508085,
      "net_gex": 1005809.1240194385,
      "expiry": "2026-05-15"
    },
    {
      "strike": 654.0,
      "call_gex": 1842679.9913229076,
      "put_gex": -157999.7371029923,
      "net_gex": 1684680.2542199153,
      "expiry": "2026-05-15"
    },
    {
      "strike": 655.0,
      "call_gex": 3549382.4383714586,
      "put_gex": -644694.4852447069,
      "net_gex": 2904687.953126752,
      "expiry": "2026-05-152026-05-182026-05-192026-05-20"
    },
    {
      "strike": 656.0,
      "call_gex": 1524919.7990042076,
      "put_gex": -172514.54504720322,
      "net_gex": 1352405.2539570043,
      "expiry": "2026-05-15"
    },
    {
      "strike": 657.0,
      "call_gex": 1860947.1217736646,
      "put_gex": -137099.34102232,
      "net_gex": 1723847.7807513445,
      "expiry": "2026-05-15"
    },
    {
      "strike": 658.0,
      "call_gex": 1644999.5192258302,
      "put_gex": -116305.54328562217,
      "net_gex": 1528693.975940208,
      "expiry": "2026-05-15"
    },
    {
      "strike": 659.0,
      "call_gex": 898864.7539624495,
      "put_gex": -150683.33045500916,
      "net_gex": 748181.4235074404,
      "expiry": "2026-05-15"
    },
    {
      "strike": 660.0,
      "call_gex": 16592904.400034398,
      "put_gex": -2267559.7753704158,
      "net_gex": 14325344.624663983,
      "expiry": "2026-05-152026-05-182026-05-192026-05-20"
    },
    {
      "strike": 661.0,
      "call_gex": 1004566.8644147045,
      "put_gex": -129594.86649639143,
      "net_gex": 874971.997918313,
      "expiry": "2026-05-15"
    },
    {
      "strike": 662.0,
      "call_gex": 1437144.4001933932,
      "put_gex": -198255.6713375079,
      "net_gex": 1238888.7288558853,
      "expiry": "2026-05-15"
    },
    {
      "strike": 663.0,
      "call_gex": 1571764.0756149362,
      "put_gex": -91096.80274658914,
      "net_gex": 1480667.2728683471,
      "expiry": "2026-05-15"
    },
    {
      "strike": 664.0,
      "call_gex": 1932793.3324705847,
      "put_gex": -117457.88557887494,
      "net_gex": 1815335.4468917097,
      "expiry": "2026-05-15"
    },
    {
      "strike": 665.0,
      "call_gex": 10120724.226007264,
      "put_gex": -1408172.446287839,
      "net_gex": 8712551.779719425,
      "expiry": "2026-05-152026-05-182026-05-192026-05-20"
    },
    {
      "strike": 666.0,
      "call_gex": 1397848.6884553067,
      "put_gex": -180856.312962145,
      "net_gex": 1216992.3754931616,
      "expiry": "2026-05-15"
    },
    {
      "strike": 667.0,
      "call_gex": 3594100.300357194,
      "put_gex": -148070.99225103974,
      "net_gex": 3446029.308106154,
      "expiry": "2026-05-15"
    },
    {
      "strike": 668.0,
      "call_gex": 2245309.102324552,
      "put_gex": -1365950.5369107698,
      "net_gex": 879358.5654137821,
      "expiry": "2026-05-15"
    },
    {
      "strike": 669.0,
      "call_gex": 1891565.773884738,
      "put_gex": -435797.69933309767,
      "net_gex": 1455768.0745516405,
      "expiry": "2026-05-15"
    },
    {
      "strike": 670.0,
      "call_gex": 12894143.879769653,
      "put_gex": -2475212.2074124725,
      "net_gex": 10418931.672357181,
      "expiry": "2026-05-152026-05-182026-05-192026-05-20"
    },
    {
      "strike": 671.0,
      "call_gex": 9764414.642723994,
      "put_gex": -217181.27953709915,
      "net_gex": 9547233.363186896,
      "expiry": "2026-05-15"
    },
    {
      "strike": 672.0,
      "call_gex": 2635311.3190498687,
      "put_gex": -258893.69162632764,
      "net_gex": 2376417.627423541,
      "expiry": "2026-05-15"
    },
    {
      "strike": 673.0,
      "call_gex": 4291102.030463064,
      "put_gex": -1601721.173810737,
      "net_gex": 2689380.856652327,
      "expiry": "2026-05-15"
    },
    {
      "strike": 674.0,
      "call_gex": 5741094.060608219,
      "put_gex": -1013952.8383242487,
      "net_gex": 4727141.222283971,
      "expiry": "2026-05-15"
    },
    {
      "strike": 675.0,
      "call_gex": 22078834.48215106,
      "put_gex": -5803221.393015627,
      "net_gex": 16275613.089135433,
      "expiry": "2026-05-152026-05-182026-05-192026-05-20"
    },
    {
      "strike": 676.0,
      "call_gex": 2966760.271099126,
      "put_gex": -2186246.7888474856,
      "net_gex": 780513.4822516404,
      "expiry": "2026-05-15"
    },
    {
      "strike": 677.0,
      "call_gex": 4390943.889038748,
      "put_gex": -153139.83077350777,
      "net_gex": 4237804.05826524,
      "expiry": "2026-05-15"
    },
    {
      "strike": 678.0,
      "call_gex": 4436471.888673048,
      "put_gex": -562472.3562230798,
      "net_gex": 3873999.5324499677,
      "expiry": "2026-05-15"
    },
    {
      "strike": 679.0,
      "call_gex": 3556233.0319898864,
      "put_gex": -383426.5851245858,
      "net_gex": 3172806.4468653006,
      "expiry": "2026-05-15"
    },
    {
      "strike": 680.0,
      "call_gex": 28442547.809330348,
      "put_gex": -7530306.025867044,
      "net_gex": 20912241.783463307,
      "expiry": "2026-05-152026-05-182026-05-192026-05-20"
    },
    {
      "strike": 681.0,
      "call_gex": 3053170.2096787845,
      "put_gex": -370761.3969174482,
      "net_gex": 2682408.812761336,
      "expiry": "2026-05-15"
    },
    {
      "strike": 682.0,
      "call_gex": 4401600.641904884,
      "put_gex": -231117.2488184728,
      "net_gex": 4170483.393086411,
      "expiry": "2026-05-15"
    },
    {
      "strike": 683.0,
      "call_gex": 4525491.395868702,
      "put_gex": -675122.6443796523,
      "net_gex": 3850368.7514890498,
      "expiry": "2026-05-15"
    },
    {
      "strike": 684.0,
      "call_gex": 2943496.0691289282,
      "put_gex": -7081388.828393981,
      "net_gex": -4137892.7592650526,
      "expiry": "2026-05-15"
    },
    {
      "strike": 685.0,
      "call_gex": 28139550.94742577,
      "put_gex": -8486876.042562544,
      "net_gex": 19652674.904863227,
      "expiry": "2026-05-152026-05-182026-05-192026-05-20"
    },
    {
      "strike": 686.0,
      "call_gex": 4182928.2355196155,
      "put_gex": -1028710.1376499642,
      "net_gex": 3154218.0978696514,
      "expiry": "2026-05-152026-05-182026-05-192026-05-20"
    },
    {
      "strike": 687.0,
      "call_gex": 6608634.176692511,
      "put_gex": -610324.6118510042,
      "net_gex": 5998309.564841506,
      "expiry": "2026-05-152026-05-182026-05-192026-05-20"
    },
    {
      "strike": 688.0,
      "call_gex": 5046101.887588313,
      "put_gex": -1648035.1264475356,
      "net_gex": 3398066.7611407773,
      "expiry": "2026-05-152026-05-182026-05-192026-05-20"
    },
    {
      "strike": 689.0,
      "call_gex": 4814337.377006663,
      "put_gex": -2025082.1231090282,
      "net_gex": 2789255.2538976353,
      "expiry": "2026-05-152026-05-182026-05-192026-05-20"
    },
    {
      "strike": 690.0,
      "call_gex": 47716134.11290109,
      "put_gex": -20659202.64329139,
      "net_gex": 27056931.4696097,
      "expiry": "2026-05-152026-05-182026-05-192026-05-20"
    },
    {
      "strike": 691.0,
      "call_gex": 4687114.234984972,
      "put_gex": -821485.3539866218,
      "net_gex": 3865628.8809983493,
      "expiry": "2026-05-152026-05-182026-05-192026-05-20"
    },
    {
      "strike": 692.0,
      "call_gex": 4025640.841023316,
      "put_gex": -3179050.09091169,
      "net_gex": 846590.7501116261,
      "expiry": "2026-05-152026-05-182026-05-192026-05-20"
    },
    {
      "strike": 693.0,
      "call_gex": 7946522.735556431,
      "put_gex": -1333918.1647233996,
      "net_gex": 6612604.570833032,
      "expiry": "2026-05-152026-05-182026-05-192026-05-20"
    },
    {
      "strike": 694.0,
      "call_gex": 5532334.391632451,
      "put_gex": -680007.8241867097,
      "net_gex": 4852326.567445741,
      "expiry": "2026-05-152026-05-182026-05-192026-05-20"
    },
    {
      "strike": 695.0,
      "call_gex": 13849046.589736912,
      "put_gex": -5674365.239879607,
      "net_gex": 8174681.349857305,
      "expiry": "2026-05-152026-05-182026-05-192026-05-20"
    },
    {
      "strike": 696.0,
      "call_gex": 9691007.739692686,
      "put_gex": -3193533.141964591,
      "net_gex": 6497474.597728094,
      "expiry": "2026-05-152026-05-182026-05-192026-05-20"
    },
    {
      "strike": 697.0,
      "call_gex": 5409659.10436731,
      "put_gex": -662032.2341834499,
      "net_gex": 4747626.870183861,
      "expiry": "2026-05-152026-05-182026-05-192026-05-20"
    },
    {
      "strike": 698.0,
      "call_gex": 7164197.693532633,
      "put_gex": -2097648.1906414935,
      "net_gex": 5066549.50289114,
      "expiry": "2026-05-152026-05-182026-05-192026-05-20"
    },
    {
      "strike": 699.0,
      "call_gex": 8750303.865359938,
      "put_gex": -2385583.6219541896,
      "net_gex": 6364720.243405747,
      "expiry": "2026-05-152026-05-182026-05-192026-05-20"
    },
    {
      "strike": 700.0,
      "call_gex": 126136590.28312485,
      "put_gex": -21712904.369446885,
      "net_gex": 104423685.91367795,
      "expiry": "2026-05-152026-05-182026-05-192026-05-20"
    },
    {
      "strike": 701.0,
      "call_gex": 10145021.76589149,
      "put_gex": -2140529.862885004,
      "net_gex": 8004491.9030064875,
      "expiry": "2026-05-152026-05-182026-05-192026-05-20"
    },
    {
      "strike": 702.0,
      "call_gex": 12139987.610707214,
      "put_gex": -1659244.0103602894,
      "net_gex": 10480743.600346925,
      "expiry": "2026-05-152026-05-182026-05-192026-05-20"
    },
    {
      "strike": 703.0,
      "call_gex": 16377993.448880501,
      "put_gex": -1600971.5465373045,
      "net_gex": 14777021.902343197,
      "expiry": "2026-05-152026-05-182026-05-192026-05-20"
    },
    {
      "strike": 704.0,
      "call_gex": 9664808.04396961,
      "put_gex": -2811002.191570676,
      "net_gex": 6853805.852398935,
      "expiry": "2026-05-152026-05-182026-05-192026-05-20"
    },
    {
      "strike": 705.0,
      "call_gex": 31967876.40559763,
      "put_gex": -7694125.050986319,
      "net_gex": 24273751.354611315,
      "expiry": "2026-05-152026-05-182026-05-192026-05-20"
    },
    {
      "strike": 706.0,
      "call_gex": 9955010.976140259,
      "put_gex": -8339206.315988844,
      "net_gex": 1615804.660151415,
      "expiry": "2026-05-152026-05-182026-05-192026-05-20"
    },
    {
      "strike": 707.0,
      "call_gex": 12537128.80445839,
      "put_gex": -5244575.100660963,
      "net_gex": 7292553.703797428,
      "expiry": "2026-05-152026-05-182026-05-192026-05-20"
    },
    {
      "strike": 708.0,
      "call_gex": 14780871.95638976,
      "put_gex": -6003519.909671678,
      "net_gex": 8777352.046718081,
      "expiry": "2026-05-152026-05-182026-05-192026-05-20"
    },
    {
      "strike": 709.0,
      "call_gex": 18272093.49080355,
      "put_gex": -5747050.938281344,
      "net_gex": 12525042.552522207,
      "expiry": "2026-05-152026-05-182026-05-192026-05-20"
    },
    {
      "strike": 710.0,
      "call_gex": 115432584.49040243,
      "put_gex": -19103368.35366544,
      "net_gex": 96329216.136737,
      "expiry": "2026-05-152026-05-182026-05-192026-05-20"
    },
    {
      "strike": 711.0,
      "call_gex": 45569244.22557053,
      "put_gex": -5977258.335692587,
      "net_gex": 39591985.889877945,
      "expiry": "2026-05-152026-05-182026-05-192026-05-20"
    },
    {
      "strike": 712.0,
      "call_gex": 33101594.641036518,
      "put_gex": -9897980.392237524,
      "net_gex": 23203614.248798992,
      "expiry": "2026-05-152026-05-182026-05-192026-05-20"
    },
    {
      "strike": 713.0,
      "call_gex": 26515119.473389912,
      "put_gex": -5729480.2441300675,
      "net_gex": 20785639.22925984,
      "expiry": "2026-05-152026-05-182026-05-192026-05-20"
    },
    {
      "strike": 714.0,
      "call_gex": 21669785.2254094,
      "put_gex": -8444594.966288144,
      "net_gex": 13225190.25912126,
      "expiry": "2026-05-152026-05-182026-05-192026-05-20"
    },
    {
      "strike": 715.0,
      "call_gex": 56344044.2201828,
      "put_gex": -24905652.157443885,
      "net_gex": 31438392.062738914,
      "expiry": "2026-05-152026-05-182026-05-192026-05-20"
    },
    {
      "strike": 716.0,
      "call_gex": 8449702.664269892,
      "put_gex": -10662532.352564104,
      "net_gex": -2212829.6882942114,
      "expiry": "2026-05-152026-05-182026-05-192026-05-20"
    },
    {
      "strike": 717.0,
      "call_gex": 16176681.842744596,
      "put_gex": -19390558.675509933,
      "net_gex": -3213876.832765338,
      "expiry": "2026-05-152026-05-182026-05-192026-05-20"
    },
    {
      "strike": 718.0,
      "call_gex": 25160765.818275914,
      "put_gex": -24651717.409898598,
      "net_gex": 509048.4083773126,
      "expiry": "2026-05-152026-05-182026-05-192026-05-20"
    },
    {
      "strike": 719.0,
      "call_gex": 17828231.898745846,
      "put_gex": -14801021.121038983,
      "net_gex": 3027210.777706864,
      "expiry": "2026-05-152026-05-182026-05-192026-05-20"
    },
    {
      "strike": 720.0,
      "call_gex": 134777838.97892708,
      "put_gex": -71035339.0223139,
      "net_gex": 63742499.9566132,
      "expiry": "2026-05-152026-05-182026-05-192026-05-20"
    },
    {
      "strike": 721.0,
      "call_gex": 45668930.17428384,
      "put_gex": -17451211.228406418,
      "net_gex": 28217718.945877418,
      "expiry": "2026-05-152026-05-182026-05-192026-05-20"
    },
    {
      "strike": 722.0,
      "call_gex": 41156480.79736337,
      "put_gex": -28208685.936039098,
      "net_gex": 12947794.86132427,
      "expiry": "2026-05-152026-05-182026-05-192026-05-20"
    },
    {
      "strike": 723.0,
      "call_gex": 72763358.21281461,
      "put_gex": -27505526.615163993,
      "net_gex": 45257831.59765062,
      "expiry": "2026-05-152026-05-182026-05-192026-05-20"
    },
    {
      "strike": 724.0,
      "call_gex": 39069638.66086805,
      "put_gex": -43919016.491696134,
      "net_gex": -4849377.830828087,
      "expiry": "2026-05-152026-05-182026-05-192026-05-20"
    },
    {
      "strike": 725.0,
      "call_gex": 109093254.6103021,
      "put_gex": -99679513.10993221,
      "net_gex": 9413741.500369886,
      "expiry": "2026-05-152026-05-182026-05-192026-05-20"
    },
    {
      "strike": 726.0,
      "call_gex": 46206999.50965913,
      "put_gex": -29986764.360479634,
      "net_gex": 16220235.149179488,
      "expiry": "2026-05-152026-05-182026-05-192026-05-20"
    },
    {
      "strike": 727.0,
      "call_gex": 24416952.08332807,
      "put_gex": -49224198.527768925,
      "net_gex": -24807246.444440857,
      "expiry": "2026-05-152026-05-182026-05-192026-05-20"
    },
    {
      "strike": 728.0,
      "call_gex": 41949999.90496007,
      "put_gex": -53218427.326094136,
      "net_gex": -11268427.42113406,
      "expiry": "2026-05-152026-05-182026-05-192026-05-20"
    },
    {
      "strike": 729.0,
      "call_gex": 33471138.809953522,
      "put_gex": -46293259.40244654,
      "net_gex": -12822120.59249302,
      "expiry": "2026-05-152026-05-182026-05-192026-05-20"
    },
    {
      "strike": 730.0,
      "call_gex": 218410594.01634482,
      "put_gex": -472599914.74192876,
      "net_gex": -254189320.72558397,
      "expiry": "2026-05-152026-05-182026-05-192026-05-20"
    },
    {
      "strike": 731.0,
      "call_gex": 106539693.30085821,
      "put_gex": -91386822.93933228,
      "net_gex": 15152870.361525934,
      "expiry": "2026-05-152026-05-182026-05-192026-05-20"
    },
    {
      "strike": 732.0,
      "call_gex": 197878779.29895595,
      "put_gex": -316489401.92007726,
      "net_gex": -118610622.62112132,
      "expiry": "2026-05-152026-05-182026-05-192026-05-20"
    },
    {
      "strike": 733.0,
      "call_gex": 232205552.40026376,
      "put_gex": -309824348.0726362,
      "net_gex": -77618795.67237243,
      "expiry": "2026-05-152026-05-182026-05-192026-05-20"
    },
    {
      "strike": 734.0,
      "call_gex": 95686113.01601803,
      "put_gex": -202295622.47068155,
      "net_gex": -106609509.45466352,
      "expiry": "2026-05-152026-05-182026-05-192026-05-20"
    },
    {
      "strike": 735.0,
      "call_gex": 285202623.9971775,
      "put_gex": -891681345.4220086,
      "net_gex": -606478721.4248312,
      "expiry": "2026-05-152026-05-182026-05-192026-05-20"
    },
    {
      "strike": 736.0,
      "call_gex": 114636695.68800993,
      "put_gex": -562367036.2876632,
      "net_gex": -447730340.59965324,
      "expiry": "2026-05-152026-05-182026-05-192026-05-20"
    },
    {
      "strike": 737.0,
      "call_gex": 197535411.9612498,
      "put_gex": -526477386.41400135,
      "net_gex": -328941974.4527515,
      "expiry": "2026-05-152026-05-182026-05-192026-05-20"
    },
    {
      "strike": 738.0,
      "call_gex": 165015923.25251672,
      "put_gex": -1319167533.570081,
      "net_gex": -1154151610.3175642,
      "expiry": "2026-05-152026-05-182026-05-192026-05-20"
    },
    {
      "strike": 739.0,
      "call_gex": 161820708.24192443,
      "put_gex": -1036577728.3995165,
      "net_gex": -874757020.157592,
      "expiry": "2026-05-152026-05-182026-05-192026-05-20"
    },
    {
      "strike": 740.0,
      "call_gex": 381900363.37102824,
      "put_gex": -1954110136.1572998,
      "net_gex": -1572209772.7862713,
      "expiry": "2026-05-152026-05-182026-05-192026-05-20"
    },
    {
      "strike": 741.0,
      "call_gex": 216633165.24269867,
      "put_gex": -941286077.9189175,
      "net_gex": -724652912.6762189,
      "expiry": "2026-05-152026-05-182026-05-192026-05-20"
    },
    {
      "strike": 742.0,
      "call_gex": 333829687.34537727,
      "put_gex": -114362759.20060718,
      "net_gex": 219466928.1447701,
      "expiry": "2026-05-152026-05-182026-05-192026-05-20"
    },
    {
      "strike": 743.0,
      "call_gex": 228029414.9351427,
      "put_gex": -144776442.2237703,
      "net_gex": 83252972.7113724,
      "expiry": "2026-05-152026-05-182026-05-192026-05-20"
    },
    {
      "strike": 744.0,
      "call_gex": 227667689.0167427,
      "put_gex": -89192536.81427035,
      "net_gex": 138475152.20247236,
      "expiry": "2026-05-152026-05-182026-05-192026-05-20"
    },
    {
      "strike": 745.0,
      "call_gex": 600734959.0395273,
      "put_gex": -64299876.89694038,
      "net_gex": 536435082.1425869,
      "expiry": "2026-05-152026-05-182026-05-192026-05-20"
    },
    {
      "strike": 746.0,
      "call_gex": 307176626.4834051,
      "put_gex": -16612312.338896215,
      "net_gex": 290564314.1445089,
      "expiry": "2026-05-152026-05-182026-05-192026-05-20"
    },
    {
      "strike": 747.0,
      "call_gex": 226169797.9546297,
      "put_gex": -15123150.11785223,
      "net_gex": 211046647.83677745,
      "expiry": "2026-05-152026-05-182026-05-192026-05-20"
    },
    {
      "strike": 748.0,
      "call_gex": 194751062.72748527,
      "put_gex": 0.0,
      "net_gex": 194751062.72748527,
      "expiry": "2026-05-152026-05-182026-05-192026-05-20"
    },
    {
      "strike": 749.0,
      "call_gex": 185612190.9230963,
      "put_gex": 0.0,
      "net_gex": 185612190.9230963,
      "expiry": "2026-05-152026-05-182026-05-192026-05-20"
    },
    {
      "strike": 750.0,
      "call_gex": 282824770.5687973,
      "put_gex": 0.0,
      "net_gex": 282824770.5687973,
      "expiry": "2026-05-152026-05-182026-05-192026-05-20"
    },
    {
      "strike": 751.0,
      "call_gex": 98923034.30328466,
      "put_gex": 0.0,
      "net_gex": 98923034.30328466,
      "expiry": "2026-05-15"
    },
    {
      "strike": 752.0,
      "call_gex": 24062000.113465115,
      "put_gex": 0.0,
      "net_gex": 24062000.113465115,
      "expiry": "2026-05-15"
    },
    {
      "strike": 753.0,
      "call_gex": 30634280.86002482,
      "put_gex": 0.0,
      "net_gex": 30634280.86002482,
      "expiry": "2026-05-15"
    },
    {
      "strike": 754.0,
      "call_gex": 36082134.00143423,
      "put_gex": 0.0,
      "net_gex": 36082134.00143423,
      "expiry": "2026-05-15"
    },
    {
      "strike": 755.0,
      "call_gex": 99761323.56575724,
      "put_gex": 0.0,
      "net_gex": 99761323.56575724,
      "expiry": "2026-05-152026-05-182026-05-192026-05-20"
    },
    {
      "strike": 756.0,
      "call_gex": 12109850.795055978,
      "put_gex": 0.0,
      "net_gex": 12109850.795055978,
      "expiry": "2026-05-15"
    },
    {
      "strike": 757.0,
      "call_gex": 0.0,
      "put_gex": 0.0,
      "net_gex": 0.0,
      "expiry": "2026-05-15"
    },
    {
      "strike": 758.0,
      "call_gex": 0.0,
      "put_gex": 0.0,
      "net_gex": 0.0,
      "expiry": "2026-05-15"
    },
    {
      "strike": 760.0,
      "call_gex": 33596383.21107414,
      "put_gex": 0.0,
      "net_gex": 33596383.21107414,
      "expiry": "2026-05-152026-05-182026-05-192026-05-20"
    },
    {
      "strike": 762.0,
      "call_gex": 0.0,
      "put_gex": 0.0,
      "net_gex": 0.0,
      "expiry": "2026-05-15"
    },
    {
      "strike": 764.0,
      "call_gex": 0.0,
      "put_gex": 0.0,
      "net_gex": 0.0,
      "expiry": "2026-05-15"
    },
    {
      "strike": 765.0,
      "call_gex": 9605621.950463608,
      "put_gex": 0.0,
      "net_gex": 9605621.950463608,
      "expiry": "2026-05-152026-05-182026-05-192026-05-20"
    },
    {
      "strike": 766.0,
      "call_gex": 0.0,
      "put_gex": 0.0,
      "net_gex": 0.0,
      "expiry": "2026-05-15"
    },
    {
      "strike": 770.0,
      "call_gex": 4321998.575964482,
      "put_gex": 0.0,
      "net_gex": 4321998.575964482,
      "expiry": "2026-05-152026-05-182026-05-192026-05-20"
    },
    {
      "strike": 775.0,
      "call_gex": 3250264.698824345,
      "put_gex": 0.0,
      "net_gex": 3250264.698824345,
      "expiry": "2026-05-152026-05-182026-05-192026-05-20"
    },
    {
      "strike": 780.0,
      "call_gex": 2648391.768572654,
      "put_gex": 0.0,
      "net_gex": 2648391.768572654,
      "expiry": "2026-05-152026-05-182026-05-192026-05-20"
    },
    {
      "strike": 785.0,
      "call_gex": 2520914.021261339,
      "put_gex": 0.0,
      "net_gex": 2520914.021261339,
      "expiry": "2026-05-152026-05-182026-05-192026-05-20"
    },
    {
      "strike": 790.0,
      "call_gex": 2088013.075055865,
      "put_gex": 0.0,
      "net_gex": 2088013.075055865,
      "expiry": "2026-05-152026-05-182026-05-192026-05-20"
    },
    {
      "strike": 795.0,
      "call_gex": 938669.928000374,
      "put_gex": 0.0,
      "net_gex": 938669.928000374,
      "expiry": "2026-05-152026-05-182026-05-192026-05-20"
    },
    {
      "strike": 800.0,
      "call_gex": 1020569.7442842291,
      "put_gex": 0.0,
      "net_gex": 1020569.7442842291,
      "expiry": "2026-05-152026-05-182026-05-192026-05-20"
    },
    {
      "strike": 805.0,
      "call_gex": 696185.3428214903,
      "put_gex": 0.0,
      "net_gex": 696185.3428214903,
      "expiry": "2026-05-152026-05-20"
    },
    {
      "strike": 810.0,
      "call_gex": 592145.0741939021,
      "put_gex": 0.0,
      "net_gex": 592145.0741939021,
      "expiry": "2026-05-152026-05-182026-05-19"
    },
    {
      "strike": 815.0,
      "call_gex": 624380.296111579,
      "put_gex": 0.0,
      "net_gex": 624380.296111579,
      "expiry": "2026-05-152026-05-182026-05-20"
    },
    {
      "strike": 820.0,
      "call_gex": 204614.321620671,
      "put_gex": 0.0,
      "net_gex": 204614.321620671,
      "expiry": "2026-05-152026-05-182026-05-19"
    },
    {
      "strike": 825.0,
      "call_gex": 341860.41941954906,
      "put_gex": 0.0,
      "net_gex": 341860.41941954906,
      "expiry": "2026-05-152026-05-182026-05-192026-05-20"
    },
    {
      "strike": 830.0,
      "call_gex": 212719.89622604084,
      "put_gex": 0.0,
      "net_gex": 212719.89622604084,
      "expiry": "2026-05-152026-05-182026-05-20"
    },
    {
      "strike": 835.0,
      "call_gex": 60208.399350120875,
      "put_gex": 0.0,
      "net_gex": 60208.399350120875,
      "expiry": "2026-05-152026-05-182026-05-20"
    },
    {
      "strike": 840.0,
      "call_gex": 14937.673764255393,
      "put_gex": 0.0,
      "net_gex": 14937.673764255393,
      "expiry": "2026-05-152026-05-20"
    },
    {
      "strike": 845.0,
      "call_gex": 55763.68799519641,
      "put_gex": 0.0,
      "net_gex": 55763.68799519641,
      "expiry": "2026-05-152026-05-19"
    },
    {
      "strike": 850.0,
      "call_gex": 220275.79630113082,
      "put_gex": 0.0,
      "net_gex": 220275.79630113082,
      "expiry": "2026-05-152026-05-19"
    },
    {
      "strike": 855.0,
      "call_gex": 378602.96172681224,
      "put_gex": 0.0,
      "net_gex": 378602.96172681224,
      "expiry": "2026-05-152026-05-20"
    },
    {
      "strike": 860.0,
      "call_gex": 135922.0810586362,
      "put_gex": 0.0,
      "net_gex": 135922.0810586362,
      "expiry": "2026-05-152026-05-18"
    },
    {
      "strike": 865.0,
      "call_gex": 463566.0673343124,
      "put_gex": 0.0,
      "net_gex": 463566.0673343124,
      "expiry": "2026-05-15"
    },
    {
      "strike": 870.0,
      "call_gex": 93007.86340572193,
      "put_gex": 0.0,
      "net_gex": 93007.86340572193,
      "expiry": "2026-05-15"
    },
    {
      "strike": 875.0,
      "call_gex": 342518.12411556597,
      "put_gex": 0.0,
      "net_gex": 342518.12411556597,
      "expiry": "2026-05-15"
    },
    {
      "strike": 880.0,
      "call_gex": 162224.60303704828,
      "put_gex": 0.0,
      "net_gex": 162224.60303704828,
      "expiry": "2026-05-15"
    },
    {
      "strike": 885.0,
      "call_gex": 180542.48751118418,
      "put_gex": 0.0,
      "net_gex": 180542.48751118418,
      "expiry": "2026-05-15"
    },
    {
      "strike": 890.0,
      "call_gex": 97533.2315780481,
      "put_gex": 0.0,
      "net_gex": 97533.2315780481,
      "expiry": "2026-05-15"
    },
    {
      "strike": 895.0,
      "call_gex": 679.8598080080741,
      "put_gex": 0.0,
      "net_gex": 679.8598080080741,
      "expiry": "2026-05-15"
    },
    {
      "strike": 900.0,
      "call_gex": 153.4772134518609,
      "put_gex": 0.0,
      "net_gex": 153.4772134518609,
      "expiry": "2026-05-15"
    },
    {
      "strike": 905.0,
      "call_gex": 574.3806301876766,
      "put_gex": 0.0,
      "net_gex": 574.3806301876766,
      "expiry": "2026-05-15"
    },
    {
      "strike": 910.0,
      "call_gex": 10513.215893682871,
      "put_gex": 0.0,
      "net_gex": 10513.215893682871,
      "expiry": "2026-05-15"
    },
    {
      "strike": 915.0,
      "call_gex": 138.73721152647298,
      "put_gex": 0.0,
      "net_gex": 138.73721152647298,
      "expiry": "2026-05-15"
    },
    {
      "strike": 920.0,
      "call_gex": 864.8462550275999,
      "put_gex": 0.0,
      "net_gex": 864.8462550275999,
      "expiry": "2026-05-15"
    },
    {
      "strike": 930.0,
      "call_gex": 1078.7215195038766,
      "put_gex": 0.0,
      "net_gex": 1078.7215195038766,
      "expiry": "2026-05-15"
    },
    {
      "strike": 940.0,
      "call_gex": 33407.76460642097,
      "put_gex": 0.0,
      "net_gex": 33407.76460642097,
      "expiry": "2026-05-15"
    },
    {
      "strike": 945.0,
      "call_gex": 2714.9184677276803,
      "put_gex": 0.0,
      "net_gex": 2714.9184677276803,
      "expiry": "2026-05-15"
    },
    {
      "strike": 950.0,
      "call_gex": 3823.500240606644,
      "put_gex": 0.0,
      "net_gex": 3823.500240606644,
      "expiry": "2026-05-15"
    },
    {
      "strike": 955.0,
      "call_gex": 6908.520649309886,
      "put_gex": 0.0,
      "net_gex": 6908.520649309886,
      "expiry": "2026-05-15"
    },
    {
      "strike": 960.0,
      "call_gex": 40570.2714263019,
      "put_gex": 0.0,
      "net_gex": 40570.2714263019,
      "expiry": "2026-05-15"
    },
    {
      "strike": 965.0,
      "call_gex": 80919.39164398589,
      "put_gex": 0.0,
      "net_gex": 80919.39164398589,
      "expiry": "2026-05-15"
    },
    {
      "strike": 970.0,
      "call_gex": 35645.542062755216,
      "put_gex": 0.0,
      "net_gex": 35645.542062755216,
      "expiry": "2026-05-15"
    },
    {
      "strike": 975.0,
      "call_gex": 46684.74982258196,
      "put_gex": 0.0,
      "net_gex": 46684.74982258196,
      "expiry": "2026-05-15"
    },
    {
      "strike": 980.0,
      "call_gex": 113.48743629016431,
      "put_gex": 0.0,
      "net_gex": 113.48743629016431,
      "expiry": "2026-05-15"
    },
    {
      "strike": 985.0,
      "call_gex": 10967.2973466519,
      "put_gex": 0.0,
      "net_gex": 10967.2973466519,
      "expiry": "2026-05-15"
    },
    {
      "strike": 990.0,
      "call_gex": 8834.327191615886,
      "put_gex": 0.0,
      "net_gex": 8834.327191615886,
      "expiry": "2026-05-15"
    },
    {
      "strike": 995.0,
      "call_gex": 4054.1010997050244,
      "put_gex": 0.0,
      "net_gex": 4054.1010997050244,
      "expiry": "2026-05-15"
    },
    {
      "strike": 1000.0,
      "call_gex": 4770.228304047236,
      "put_gex": 0.0,
      "net_gex": 4770.228304047236,
      "expiry": "2026-05-15"
    }
  ]
}